{"0511bbe2.jpg":"51_0511bbe2.jpg","0a48363i.jpg":"34_0a48363i.jpg","1259142j.jpg":"38_1259142j.jpg","17b50f3i.jpg":"75_17b50f3i.jpg","1d4c482i.jpg":"17_1d4c482i.jpg","1dcd772i.jpg":"67_1dcd772i.jpg","2aa49ado.jpg":"25_2aa49ado.jpg","2abffc63.jpg":"73_2abffc63.jpg","2ac347cs.jpg":"80_2ac347cs.jpg","2c5a9c3i.jpg":"52_2c5a9c3i.jpg","341e24ib.jpg":"58_341e24ib.jpg","380c8c2i.jpg":"21_380c8c2i.jpg","3d32912i.jpg":"77_3d32912i.jpg","3e71be3i.jpg":"62_3e71be3i.jpg","423655sg.jpg":"70_423655sg.jpg","54ef0bzm.jpg":"23_54ef0bzm.jpg","57ca682h.jpg":"20_57ca682h.jpg","603e7c3i.jpg":"49_603e7c3i.jpg","6168e3eq.jpg":"15_6168e3eq.jpg","62bebdsg.jpg":"65_62bebdsg.jpg","663d31o.jpeg":"66_663d31o.jpeg","66b98b2h.jpg":"59_66b98b2h.jpg","6afd8d2d.jpg":"61_6afd8d2d.jpg","6b53ddf4.jpg":"73_6b53ddf4.jpg","767710x5.jpg":"54_767710x5.jpg","7c2fba3i.jpg":"79_7c2fba3i.jpg","88afc73i.jpg":"31_88afc73i.jpg","905ae42i.jpg":"64_905ae42i.jpg","90f703sg.jpg":"19_90f703sg.jpg","9b3a11cs.jpg":"0_9b3a11cs.jpg","9fec0c3m.jpg":"45_9fec0c3m.jpg","a31fbdcs.jpg":"0_a31fbdcs.jpg","b05976sg.jpg":"65_b05976sg.jpg","bbcc3dn6.jpg":"24_bbcc3dn6.jpg","be4a130h.jpg":"68_be4a130h.jpg","c02922o4.jpg":"45_c02922o4.jpg","c0346eka.jpg":"30_c0346eka.jpg","c2c0c32j.jpg":"33_c2c0c32j.jpg","cfd80ey8.jpg":"4_cfd80ey8.jpg","d5ff992g.jpg":"43_d5ff992g.jpg","dab3db3i.jpg":"14_dab3db3i.jpg","dad1540h.jpg":"48_dad1540h.jpg","e1241129.jpg":"48_e1241129.jpg","e1e9b439.jpg":"46_e1e9b439.jpg","e649212h.jpg":"47_e649212h.jpg","ecf9ca3i.jpg":"35_ecf9ca3i.jpg","f430d6e5.jpg":"76_f430d6e5.jpg","f99c69tl.jpg":"68_f99c69tl.jpg","fa1d3c3i.jpg":"57_fa1d3c3i.jpg","fbdb472l.jpg":"71_fbdb472l.jpg","ff761c3i.jpg":"0_ff761c3i.jpg"}