{"070376sg.jpg":"0_070376sg.jpg","1079e8au.jpg":"0_1079e8au.jpg","1314bfd1.png":"74_1314bfd1.png","13d4f2n4.jpg":"0_13d4f2n4.jpg","2c54099w.jpg":"106_2c54099w.jpg","2cfb973i.jpg":"0_2cfb973i.jpg","3283bd31.png":"17_3283bd31.png","395e8708.png":"74_395e8708.png","3e5dafwz.jpg":"0_3e5dafwz.jpg","4170e43i.jpg":"194_4170e43i.jpg","4fb61d3i.jpg":"0_4fb61d3i.jpg","516a91mb.jpg":"0_516a91mb.jpg","574c80e3.png":"86_574c80e3.png","5e23fd3i.jpg":"194_5e23fd3i.jpg","60f18a3i.jpg":"0_60f18a3i.jpg","63c64e3i.jpg":"0_63c64e3i.jpg","75426blt.jpg":"0_75426blt.jpg","77fa38k9.jpg":"184_77fa38k9.jpg","8360e1jp.jpg":"0_8360e1jp.jpg","862ba513.png":"98_862ba513.png","8e79e963.png":"32_8e79e963.png","8f1b452o.jpg":"0_8f1b452o.jpg","9c69abys.jpg":"0_9c69abys.jpg","adc8163i.jpg":"0_adc8163i.jpg","b6b516km.jpg":"0_b6b516km.jpg","b981303f.jpg":"0_b981303f.jpg","bbf7dcgj.jpg":"191_bbf7dcgj.jpg","cc5f63du.jpg":"191_cc5f63du.jpg","ce8293f8.jpg":"111_ce8293f8.jpg","d0e71bly.jpg":"0_d0e71bly.jpg","d35ecdiq.jpg":"51_d35ecdiq.jpg","d94978mj.jpg":"0_d94978mj.jpg","fc9808ky.jpg":"0_fc9808ky.jpg","ff6c293i.jpg":"190_ff6c293i.jpg"}