{"062c46ev.jpg":"33_062c46ev.jpg","0d9cc0vk.jpg":"63_0d9cc0vk.jpg","22f913ji.jpg":"33_22f913ji.jpg","31c221c0.jpg":"123_31c221c0.jpg","3700f42i.jpg":"1_3700f42i.jpg","67943azs.jpg":"6_67943azs.jpg","693e51em.jpg":"33_693e51em.jpg","719e3eon.jpg":"16_719e3eon.jpg","7d03fa2i.jpg":"1_7d03fa2i.jpg","82a911eu.jpg":"4_82a911eu.jpg","8331caoa.jpg":"124_8331caoa.jpg","91a764px.jpg":"72_91a764px.jpg","a07b57ov.jpg":"122_a07b57ov.jpg","abcd97ja.jpg":"123_abcd97ja.jpg","b64934z5.jpg":"122_b64934z5.jpg","ba502e5b.jpg":"122_ba502e5b.jpg","c4384c8g.jpg":"123_c4384c8g.jpg","c6d1a9jf.jpg":"66_c6d1a9jf.jpg","cb7cd3fz.jpg":"72_cb7cd3fz.jpg","d281e6zm.jpg":"16_d281e6zm.jpg","d7af1ays.jpg":"122_d7af1ays.jpg","dce7532i.jpg":"1_dce7532i.jpg","ec3225d3.jpg":"123_ec3225d3.jpg","fa92542i.jpg":"1_fa92542i.jpg","faca304g.jpg":"10_faca304g.jpg"}