{"0538f1ko.jpg":"30_0538f1ko.jpg","057c0bb4.jpg":"7_057c0bb4.jpg","064e5b5a.gif":"54_064e5b5a.gif","06758d50.gif":"10_06758d50.gif","0769bc7i.gif":"112_0769bc7i.gif","0e7154iv.jpg":"23_0e7154iv.jpg","0e734e8g.gif":"92_0e734e8g.gif","0f7cbcm8.jpg":"30_0f7cbcm8.jpg","1046a17i.gif":"76_1046a17i.gif","1267eclo.jpg":"121_1267eclo.jpg","140ba73b.gif":"38_140ba73b.gif","17ed99u0.gif":"122_17ed99u0.gif","18b46ein.gif":"75_18b46ein.gif","1ae6a85k.gif":"52_1ae6a85k.gif","1b2b3fhs.jpg":"63_1b2b3fhs.jpg","1b63ebq4.jpg":"27_1b63ebq4.jpg","1bbf843c.gif":"35_1bbf843c.gif","224ec13m.jpg":"112_224ec13m.jpg","2417b134.gif":"39_2417b134.gif","2b0c735a.gif":"94_2b0c735a.gif","2b3b3bpi.jpg":"28_2b3b3bpi.jpg","2b76c73c.gif":"109_2b76c73c.gif","2c92f8g0.jpg":"116_2c92f8g0.jpg","2f740d7i.gif":"9_2f740d7i.gif","2ffb18u0.jpg":"6_2ffb18u0.jpg","3039938a.jpg":"59_3039938a.jpg","32481fk0.jpg":"100_32481fk0.jpg","35ee89ow.png":"85_35ee89ow.png","370a5csg.jpg":"18_370a5csg.jpg","394b06kc.jpg":"112_394b06kc.jpg","39c08b1c.gif":"5_39c08b1c.gif","39ccf8-y.gif":"109_39ccf8-y.gif","3d06813.jpeg":"80_3d06813.jpeg","3e3fa78c.jpg":"102_3e3fa78c.jpg","3eebabk0.jpg":"82_3eebabk0.jpg","40ef7auz.jpg":"118_40ef7auz.jpg","414e35w.jpeg":"91_414e35w.jpeg","4640fbj7.jpg":"61_4640fbj7.jpg","477ca5m.jpeg":"91_477ca5m.jpeg","47bf9f1c.gif":"38_47bf9f1c.gif","484f7538.gif":"60_484f7538.gif","48c8258.webp":"22_48c8258.webp","4a0d4a4x.gif":"114_4a0d4a4x.gif","4a3f83in.gif":"48_4a3f83in.gif","4d9d451c.gif":"38_4d9d451c.gif","5482f55k.gif":"91_5482f55k.gif","568c655i.jpg":"11_568c655i.jpg","58a8eeo.jpeg":"51_58a8eeo.jpeg","5e8a413u.jpg":"26_5e8a413u.jpg","60772738.gif":"94_60772738.gif","60ef1956.gif":"110_60ef1956.gif","623d13qs.jpg":"89_623d13qs.jpg","664f30w.jpeg":"4_664f30w.jpeg","673169dd.jpg":"42_673169dd.jpg","675ea12g.jpg":"109_675ea12g.jpg","6a13f45y.gif":"74_6a13f45y.gif","6ad5256o.jpg":"14_6ad5256o.jpg","6b2cabg0.jpg":"84_6b2cabg0.jpg","6b5d3eaq.jpg":"2_6b5d3eaq.jpg","6baa78jw.jpg":"49_6baa78jw.jpg","6d2ba78c.jpg":"99_6d2ba78c.jpg","6d729d0.jpeg":"4_6d729d0.jpeg","6ec56b7i.gif":"47_6ec56b7i.gif","6fe846b9.jpg":"105_6fe846b9.jpg","72e7d07a.gif":"112_72e7d07a.gif","7657528c.jpg":"115_7657528c.jpg","76f8fc3h.gif":"38_76f8fc3h.gif","7cecc643.jpg":"17_7cecc643.jpg","7cf15bd8.jpg":"106_7cf15bd8.jpg","7e3f304d.jpg":"122_7e3f304d.jpg","7f155din.gif":"15_7f155din.gif","7f8d0080.jpg":"62_7f8d0080.jpg","81368ctz.jpg":"49_81368ctz.jpg","8441afj9.jpg":"112_8441afj9.jpg","8603c67e.jpg":"98_8603c67e.jpg","867d138o.gif":"79_867d138o.gif","8810092k.gif":"38_8810092k.gif","8858b2es.jpg":"64_8858b2es.jpg","88ce4846.jpg":"81_88ce4846.jpg","89f0255a.gif":"38_89f0255a.gif","8d1212lh.jpg":"38_8d1212lh.jpg","920672r1.jpg":"37_920672r1.jpg","928d7eex.jpg":"38_928d7eex.jpg","932a0aqo.jpg":"8_932a0aqo.jpg","9371fe1t.jpg":"19_9371fe1t.jpg","945877aj.gif":"90_945877aj.gif","a01fbcje.jpg":"72_a01fbcje.jpg","a15cff7j.jpg":"27_a15cff7j.jpg","a190c19s.jpg":"81_a190c19s.jpg","a2586e87.jpg":"55_a2586e87.jpg","a8b2ack0.gif":"22_a8b2ack0.gif","ad46e5dl.jpg":"104_ad46e5dl.jpg","aeaf44sg.jpg":"88_aeaf44sg.jpg","b055204y.jpg":"71_b055204y.jpg","b2407cci.gif":"70_b2407cci.gif","b4a7ac68.gif":"40_b4a7ac68.gif","b5bfeb9g.jpg":"38_b5bfeb9g.jpg","b5f875wy.jpg":"34_b5f875wy.jpg","b68b2380.jpg":"69_b68b2380.jpg","be8a791o.jpg":"37_be8a791o.jpg","bf6ad6gi.jpg":"36_bf6ad6gi.jpg","c020cdrs.jpg":"32_c020cdrs.jpg","c059033w.jpg":"113_c059033w.jpg","c61da64z.gif":"109_c61da64z.gif","c8b2a2hs.jpg":"12_c8b2a2hs.jpg","cbced7nw.jpg":"44_cbced7nw.jpg","cf24d912.jpg":"109_cf24d912.jpg","d1dfd64g.jpg":"0_d1dfd64g.jpg","d1ef8682.jpg":"58_d1ef8682.jpg","d56fe61s.jpg":"53_d56fe61s.jpg","d594b969.gif":"91_d594b969.gif","d7b9caqo.jpg":"101_d7b9caqo.jpg","d89f1fnb.jpg":"3_d89f1fnb.jpg","e0941474.jpg":"108_e0941474.jpg","e1d627hc.jpg":"96_e1d627hc.jpg","e2d19c8.webp":"22_e2d19c8.webp","e36f765k.gif":"65_e36f765k.gif","e39211lp.jpg":"93_e39211lp.jpg","e8edb73m.jpg":"112_e8edb73m.jpg","ebbaacqo.jpg":"66_ebbaacqo.jpg","ee20475i.gif":"38_ee20475i.gif","f0ee7cw.jpeg":"91_f0ee7cw.jpeg","f1c47241.jpg":"95_f1c47241.jpg","f2d0a0mo.gif":"29_f2d0a0mo.gif","f54ac0sg.jpg":"78_f54ac0sg.jpg","f64840dm.jpg":"13_f64840dm.jpg","f77ed1tr.jpg":"77_f77ed1tr.jpg","f781dddw.jpg":"87_f781dddw.jpg","f826dc5c.jpg":"50_f826dc5c.jpg","f99f8d53.png":"16_f99f8d53.png","fb0205dw.jpg":"121_fb0205dw.jpg","fbbb114y.jpg":"37_fbbb114y.jpg","fe69eefz.jpg":"32_fe69eefz.jpg"}