{"0124ed44.jpg":"84_0124ed44.jpg","2618a5rz.jpg":"140_2618a5rz.jpg","3283bd31.png":"191_3283bd31.png","5db253em.jpg":"144_5db253em.jpg","6bf462rw.jpg":"61_6bf462rw.jpg","78486ag9.jpg":"162_78486ag9.jpg","79d0d16z.jpg":"131_79d0d16z.jpg","7aaefe6z.jpg":"39_7aaefe6z.jpg","7c37ebqb.jpg":"0_7c37ebqb.jpg","7e4888ww.jpg":"147_7e4888ww.jpg","84aa782i.jpg":"98_84aa782i.jpg","b2725dsg.jpg":"88_b2725dsg.jpg","b352022i.jpg":"56_b352022i.jpg","b904ces0.jpg":"69_b904ces0.jpg","bc133erw.jpg":"119_bc133erw.jpg","c2d75e88.jpg":"55_c2d75e88.jpg","cfeda5j7.jpg":"157_cfeda5j7.jpg","f832e367.png":"52_f832e367.png","fcec2d88.jpg":"142_fcec2d88.jpg"}